torchmd_net_cu11-2.4.13.dist-info/licenses/LICENSE
torchmdnet/__init__.py
torchmdnet/calculators.py
torchmdnet/data.py
torchmdnet/loss.py
torchmdnet/module.py
torchmdnet/optimize.py
torchmdnet/utils.py
torchmdnet/datasets/__init__.py
torchmdnet/datasets/ace.py
torchmdnet/datasets/ani.py
torchmdnet/datasets/comp6.py
torchmdnet/datasets/custom.py
torchmdnet/datasets/genentech.py
torchmdnet/datasets/hdf.py
torchmdnet/datasets/maceoff.py
torchmdnet/datasets/md17.py
torchmdnet/datasets/md22.py
torchmdnet/datasets/mdcath.py
torchmdnet/datasets/memdataset.py
torchmdnet/datasets/qm9.py
torchmdnet/datasets/qm9q.py
torchmdnet/datasets/spice.py
torchmdnet/datasets/water.py
torchmdnet/extensions/__init__.py
torchmdnet/extensions/ops.py
torchmdnet/extensions/torchmdnet_extensions.pyd
torchmdnet/models/__init__.py
torchmdnet/models/model.py
torchmdnet/models/output_modules.py
torchmdnet/models/tensornet.py
torchmdnet/models/torchmd_et.py
torchmdnet/models/torchmd_gn.py
torchmdnet/models/torchmd_t.py
torchmdnet/models/utils.py
torchmdnet/models/wrappers.py
torchmdnet/priors/__init__.py
torchmdnet/priors/atomref.py
torchmdnet/priors/base.py
torchmdnet/priors/coulomb.py
torchmdnet/priors/d2.py
torchmdnet/priors/zbl.py
torchmdnet/scripts/__init__.py
torchmdnet/scripts/train.py
torchmd_net_cu11-2.4.13.dist-info/METADATA
torchmd_net_cu11-2.4.13.dist-info/WHEEL
torchmd_net_cu11-2.4.13.dist-info/entry_points.txt
torchmd_net_cu11-2.4.13.dist-info/top_level.txt
torchmd_net_cu11-2.4.13.dist-info/RECORD
