Metadata-Version: 2.4
Name: torchmd-net-cu11
Version: 2.4.13
Summary: TorchMD-NET provides state-of-the-art neural networks potentials for biomolecular systems
Author-email: Acellera <info@acellera.com>
License-Expression: MIT
Project-URL: Homepage, https://github.com/torchmd/torchmd-net
Project-URL: Bug Tracker, https://github.com/torchmd/torchmd-net/issues
Classifier: Programming Language :: Python :: 3
Classifier: Operating System :: POSIX :: Linux
Requires-Python: >=3.8
License-File: LICENSE
Requires-Dist: h5py
Requires-Dist: torch==2.7.1
Requires-Dist: torch_geometric
Requires-Dist: lightning
Requires-Dist: tqdm
Requires-Dist: numpy
Requires-Dist: nvidia-cuda-runtime-cu11
Dynamic: license-file
Dynamic: requires-dist
